fastws/__init__.py
fastws/application.py
fastws/asyncapi.py
fastws/broker.py
fastws/docs.py
fastws/routing.py
fastws-0.1.7.dist-info/LICENSE
fastws-0.1.7.dist-info/METADATA
fastws-0.1.7.dist-info/WHEEL
fastws-0.1.7.dist-info/RECORD
