Metadata-Version: 2.1
Name: fastws
Version: 0.1.7
Summary: FastWS framework. A WebSocket wrapper around FastAPI with auto-documentation using AsyncAPI.
Home-page: https://github.com/endrekrohn/fastws
Keywords: fastapi,pydantic,starlette,websockets,asyncapi
Author: Endre Krohn
Author-email: endre@skript.no
Requires-Python: >=3.11,<4.0
Classifier: Development Status :: 3 - Alpha
Classifier: Framework :: AsyncIO
Classifier: Framework :: FastAPI
Classifier: Framework :: Pydantic
Classifier: Intended Audience :: Developers
Classifier: License :: OSI Approved :: MIT License
Classifier: Operating System :: POSIX
Classifier: Programming Language :: Python
Classifier: Programming Language :: Python :: 3
Classifier: Programming Language :: Python :: 3.11
Classifier: Programming Language :: Python :: 3 :: Only
Classifier: Topic :: Software Development
Classifier: Topic :: Software Development :: Libraries
Requires-Dist: fastapi (==0.100.0)
Project-URL: Documentation, https://github.com/endrekrohn/fastws
Project-URL: Repository, https://github.com/endrekrohn/fastws
